claim_extractor/__init__.py
claim_extractor/llm_extract.py
claim_extractor/prompt_logs.py
claim_extractor/schemas/__init__.py
claim_extractor/schemas/linked_trust.json
claim_extractor/schemas/linked_trust.meta
claim_extractor/schemas/loader.py
claim_extractor/schemas/simple_skill.json
claim_extractor/schemas/simple_skill.meta
linked_claims_extractor-0.2.4.dist-info/licenses/LICENSE
linked_claims_extractor-0.2.4.dist-info/METADATA
linked_claims_extractor-0.2.4.dist-info/WHEEL
linked_claims_extractor-0.2.4.dist-info/top_level.txt
linked_claims_extractor-0.2.4.dist-info/RECORD
