Metadata-Version: 2.4
Name: linked-claims-extractor
Version: 0.2.4
Summary: Extract structured claims from text
Author-email: Golda Velez <gvelez17@gmail.com>, Miriam Yee <myee058@gmail.com>
License: MIT
Project-URL: homepage, https://github.com/Cooperation-org/linked-claims-extractor
Project-URL: bug_tracker, https://github.com/Cooperation-org/linked-claims-extractor/issues
Classifier: Programming Language :: Python :: 3
Classifier: License :: OSI Approved :: MIT License
Classifier: Operating System :: OS Independent
Requires-Python: >=3.8
License-File: LICENSE
Requires-Dist: langchain-anthropic>=0.2.4
Requires-Dist: langchain-core>=0.1.0
Requires-Dist: requests>=2.25.0
Requires-Dist: python-dotenv>=1.0.0
Provides-Extra: dev
Requires-Dist: pytest>=7.0.0; extra == "dev"
Dynamic: license-file
